{"rowCount":6,"colCount":7,"type":0,"letters":"გეიმრხ","words":[{"word":"ხე","vertical":false,"rowIndex":0,"colIndex":0,"coinIndices":[0,1],"awardCoins":true},{"word":"გრემი","vertical":false,"rowIndex":2,"colIndex":0,"coinIndices":[],"awardCoins":false},{"word":"რემი","vertical":false,"rowIndex":4,"colIndex":3,"coinIndices":[],"awardCoins":false},{"word":"მეხი","vertical":true,"rowIndex":1,"colIndex":6,"coinIndices":[],"awardCoins":false},{"word":"გემი","vertical":true,"rowIndex":2,"colIndex":0,"coinIndices":[],"awardCoins":false},{"word":"მერი","vertical":true,"rowIndex":2,"colIndex":3,"coinIndices":[],"awardCoins":false}],"id":"7ec48d56d042664ef1f309f6aea7f9e3"}